chardon/__init__.py
chardon/article_builder/__init__.py
chardon/article_builder/article.py
chardon/article_builder/content.py
chardon/article_builder/text_parser.py
chardon/article_builder/summary/__init__.py
chardon/article_builder/summary/abc_table_of_content.py
chardon/article_builder/summary/list_table_of_content.py
chardon/article_builder/summary/table_table_of_content.py
chardon/code_arranger/__init__.py
chardon/code_arranger/documentation.py
chardon/code_parser/__init__.py
chardon/code_parser/language/__init__.py
chardon/code_parser/language/languageparser.py
chardon/code_parser/language/csharp/__init__.py
chardon/code_parser/language/csharp/csharp_block_parsing.py
chardon/code_parser/language/csharp/csharp_parser.py
chardon/code_parser/structure/__init__.py
chardon/code_parser/structure/array_of_type.py
chardon/code_parser/structure/class_.py
chardon/code_parser/structure/dict_of_type.py
chardon/code_parser/structure/field.py
chardon/code_parser/structure/function.py
chardon/code_parser/structure/parameter.py
chardon/code_parser/structure/specific_type.py
chardon/code_parser/structure/type.py
chardon/content_parser/__init__.py
chardon/content_parser/markdown_parser.py
chardon/content_parser/no_parser.py
chardon/documentation/__init__.py
chardon/documentation/project_manager.py
chardon/exporter/__init__.py
chardon/exporter/content_export.py
chardon/exporter/markdown_exporter.py
chardon/exporter/osbidian_flavored_markdown_exporter.py
chardon-0.0.1.dist-info/LICENSE
chardon-0.0.1.dist-info/METADATA
chardon-0.0.1.dist-info/WHEEL
chardon-0.0.1.dist-info/top_level.txt
chardon-0.0.1.dist-info/RECORD
