Metadata-Version: 2.1
Name: chardon
Version: 0.0.1
Summary: Multipurpose tool to parse input file and generate documents. Useful to auto generate browsable documentation.
Author-email: Portevent <porte@poudriere.be>
License: MIT License
Project-URL: Homepage, https://github.com/Portevent/Chardon
Project-URL: Issues, https://github.com/Portevent/Chardon/issues
Classifier: Development Status :: 2 - Pre-Alpha
Classifier: Programming Language :: Python :: 3.10
Classifier: License :: OSI Approved :: MIT License
Classifier: Operating System :: OS Independent
Classifier: Topic :: Text Processing
Requires-Python: >=3.10
License-File: LICENSE
Requires-Dist: regex
